{
  "manifestVersion": 1,
  "id": "pipelines-runs-analyzer-widget",
  "publisher": "danilocolombi",
  "version": "1.0.186",
  "name": "Pipelines Runs Analyzer Widget",
  "description": "Azure DevOps Extension",
  "categories": [
    "Azure Boards",
    "Azure Pipelines"
  ],
  "targets": [
    {
      "id": "Microsoft.VisualStudio.Services"
    }
  ],
  "icons": {
    "default": "logo.png"
  },
  "content": {
    "details": {
      "path": "overview.md"
    }
  },
  "files": [
    {
      "path": "dist",
      "addressable": true
    }
  ]
}